phoenix/evals/__init__.py
phoenix/evals/classify.py
phoenix/evals/default_audio_templates.py
phoenix/evals/default_templates.py
phoenix/evals/evaluators.py
phoenix/evals/exceptions.py
phoenix/evals/executors.py
phoenix/evals/generate.py
phoenix/evals/py.typed
phoenix/evals/rate_limiters.py
phoenix/evals/retrievals.py
phoenix/evals/span_templates.py
phoenix/evals/templates.py
phoenix/evals/tracing.py
phoenix/evals/utils.py
phoenix/evals/__generated__/__init__.py
phoenix/evals/__generated__/classification_evaluator_configs/__init__.py
phoenix/evals/__generated__/classification_evaluator_configs/_document_relevance_classification_evaluator_config.py
phoenix/evals/__generated__/classification_evaluator_configs/_hallucination_classification_evaluator_config.py
phoenix/evals/__generated__/classification_evaluator_configs/_models.py
phoenix/evals/legacy/__init__.py
phoenix/evals/legacy/classify.py
phoenix/evals/legacy/default_audio_templates.py
phoenix/evals/legacy/default_templates.py
phoenix/evals/legacy/evaluators.py
phoenix/evals/legacy/exceptions.py
phoenix/evals/legacy/executors.py
phoenix/evals/legacy/generate.py
phoenix/evals/legacy/retrievals.py
phoenix/evals/legacy/span_templates.py
phoenix/evals/legacy/templates.py
phoenix/evals/legacy/utils.py
phoenix/evals/legacy/models/__init__.py
phoenix/evals/legacy/models/anthropic.py
phoenix/evals/legacy/models/base.py
phoenix/evals/legacy/models/bedrock.py
phoenix/evals/legacy/models/google_genai.py
phoenix/evals/legacy/models/litellm.py
phoenix/evals/legacy/models/mistralai.py
phoenix/evals/legacy/models/openai.py
phoenix/evals/legacy/models/rate_limiters.py
phoenix/evals/legacy/models/vertex.py
phoenix/evals/legacy/models/vertexai.py
phoenix/evals/llm/__init__.py
phoenix/evals/llm/prompts.py
phoenix/evals/llm/registries.py
phoenix/evals/llm/types.py
phoenix/evals/llm/wrapper.py
phoenix/evals/llm/adapters/__init__.py
phoenix/evals/llm/adapters/anthropic/__init__.py
phoenix/evals/llm/adapters/anthropic/adapter.py
arize_phoenix_evals-2.7.1.dist-info/METADATA
arize_phoenix_evals-2.7.1.dist-info/WHEEL
arize_phoenix_evals-2.7.1.dist-info/licenses/IP_NOTICE
arize_phoenix_evals-2.7.1.dist-info/licenses/LICENSE
arize_phoenix_evals-2.7.1.dist-info/RECORD
