Metadata-Version: 2.4
Name: arize-phoenix-evals
Version: 2.7.1
Summary: LLM Evaluations
Project-URL: Documentation, https://arize.com/docs/phoenix/
Project-URL: Issues, https://github.com/Arize-ai/phoenix/issues
Project-URL: Source, https://github.com/Arize-ai/phoenix
Author-email: Arize AI <phoenix-devs@arize.com>
License: Elastic-2.0
License-File: IP_NOTICE
License-File: LICENSE
Keywords: Explainability,Monitoring,Observability
Classifier: Programming Language :: Python
Classifier: Programming Language :: Python :: 3.8
Classifier: Programming Language :: Python :: 3.9
Classifier: Programming Language :: Python :: 3.10
Classifier: Programming Language :: Python :: 3.11
Classifier: Programming Language :: Python :: 3.12
Classifier: Programming Language :: Python :: 3.13
Requires-Python: <3.14,>=3.8
Requires-Dist: jsonpath-ng
Requires-Dist: openinference-instrumentation>=0.1.20
Requires-Dist: openinference-semantic-conventions>=0.1.19
Requires-Dist: opentelemetry-api
Requires-Dist: pandas
Requires-Dist: pydantic>=2.0.0
Requires-Dist: pystache
Requires-Dist: tqdm
Requires-Dist: typing-extensions<5,>=4.5
Provides-Extra: dev
Requires-Dist: anthropic>0.18.0; extra == 'dev'
Requires-Dist: boto3; extra == 'dev'
Requires-Dist: litellm>=1.28.9; extra == 'dev'
Requires-Dist: mistralai>=1.0.0; extra == 'dev'
Requires-Dist: openai>=1.0.0; extra == 'dev'
Requires-Dist: vertexai; extra == 'dev'
Provides-Extra: test
Requires-Dist: anthropic>=0.18.0; extra == 'test'
Requires-Dist: boto3; extra == 'test'
Requires-Dist: lameenc; extra == 'test'
Requires-Dist: litellm>=1.28.9; extra == 'test'
Requires-Dist: mistralai>=1.0.0; extra == 'test'
Requires-Dist: nest-asyncio; extra == 'test'
Requires-Dist: openai>=1.0.0; extra == 'test'
Requires-Dist: openinference-semantic-conventions; extra == 'test'
Requires-Dist: pandas; extra == 'test'
Requires-Dist: pandas-stubs<=2.0.2.230605; extra == 'test'
Requires-Dist: respx; extra == 'test'
Requires-Dist: tqdm; extra == 'test'
Requires-Dist: types-tqdm; extra == 'test'
Requires-Dist: typing-extensions<5,>=4.5; extra == 'test'
Requires-Dist: vertexai; extra == 'test'
